[
  {
    "id": 1,
    "name": "Stark Moody",
    "username": "user1",
    "email": "user1@gmail.com",
    "password": "md5(pass)",
    "img": "https://via.placeholder.com/400/723/fff/?text=user1",
    "data_create": "2021-01-21 07:59:56 "
  },
  {
    "id": 2,
    "name": "Leach Pace",
    "username": "user2",
    "email": "user2@gmail.com",
    "password": "md5(pass)",
    "img": "https://via.placeholder.com/400/781/fff/?text=user2",
    "data_create": "2021-01-09 03:43:32 "
  },
  {
    "id": 3,
    "name": "Beatrice Mckay",
    "username": "user3",
    "email": "user3@gmail.com",
    "password": "md5(pass)",
    "img": "https://via.placeholder.com/400/786/fff/?text=user3",
    "data_create": "2021-02-14 07:57:40 "
  },
  {
    "id": 4,
    "name": "Lawanda Frazier",
    "username": "user4",
    "email": "user4@gmail.com",
    "password": "md5(pass)",
    "img": "https://via.placeholder.com/400/791/fff/?text=user4",
    "data_create": "2021-04-08 08:56:11 "
  },
  {
    "id": 5,
    "name": "Jayne Saunders",
    "username": "user5",
    "email": "user5@gmail.com",
    "password": "md5(pass)",
    "img": "https://via.placeholder.com/400/973/fff/?text=user5",
    "data_create": "2021-03-08 12:52:39 "
  },
  {
    "id": 6,
    "name": "Andrea Dean",
    "username": "user6",
    "email": "user6@gmail.com",
    "password": "md5(pass)",
    "img": "https://via.placeholder.com/400/778/fff/?text=user6",
    "data_create": "2021-03-21 01:43:38 "
  },
  {
    "id": 7,
    "name": "Tommie Parks",
    "username": "user7",
    "email": "user7@gmail.com",
    "password": "md5(pass)",
    "img": "https://via.placeholder.com/400/986/fff/?text=user7",
    "data_create": "2021-03-28 11:01:42 "
  },
  {
    "id": 8,
    "name": "Mcpherson Estrada",
    "username": "user8",
    "email": "user8@gmail.com",
    "password": "md5(pass)",
    "img": "https://via.placeholder.com/400/898/fff/?text=user8",
    "data_create": "2021-04-14 02:45:07 "
  },
  {
    "id": 9,
    "name": "Forbes Donovan",
    "username": "user9",
    "email": "user9@gmail.com",
    "password": "md5(pass)",
    "img": "https://via.placeholder.com/400/778/fff/?text=user9",
    "data_create": "2021-03-06 03:41:51 "
  },
  {
    "id": 10,
    "name": "Francisca Mosley",
    "username": "user10",
    "email": "user10@gmail.com",
    "password": "md5(pass)",
    "img": "https://via.placeholder.com/400/945/fff/?text=user10",
    "data_create": "2021-01-21 03:23:51 "
  }
]
